osupippy/beatmap.py
osupippy/diff.py
osupippy/pp.py
osupippy/types.py
osupippy-0.1.dist-info/DESCRIPTION.rst
osupippy-0.1.dist-info/METADATA
osupippy-0.1.dist-info/RECORD
osupippy-0.1.dist-info/WHEEL
osupippy-0.1.dist-info/metadata.json
osupippy-0.1.dist-info/top_level.txt
osupippy-0.1.dist-info/zip-safe
pippy/beatmap.py
pippy/diff.py
pippy/pp.py
pippy/types.py
