Metadata-Version: 2.0
Name: osupippy
Version: 0.1
Summary: pippy is a beatmap parser and pp calculator for osu!
Home-page: https://github.com/jamesguessis/pippy
Author: jamesguessis
Author-email: jamesguessis@gmail.com
License: MIT
Keywords: osu pippy peppy pp beatmap
Platform: UNKNOWN
